emailSMS/__init__.py
emailSMS/emailSMS.py
emailSMS/test.py
emailSMS_python3-0.0.7.dist-info/LICENSE
emailSMS_python3-0.0.7.dist-info/METADATA
emailSMS_python3-0.0.7.dist-info/WHEEL
emailSMS_python3-0.0.7.dist-info/top_level.txt
emailSMS_python3-0.0.7.dist-info/RECORD
