Metadata-Version: 2.1
Name: emailSMS-python3
Version: 0.0.7
Summary: Gateway between email and SMS/MMS for python3
Home-page: https://github.com/JoeWomelsdorf/emailSMS_Python
Author: Joe Womelsdorf
Author-email: josef.womelsdorf@outlook.com
License: UNKNOWN
Project-URL: Bug Tracker, https://github.com/JoeWomelsdorf/emailSMS_Python/issues
Platform: UNKNOWN
Classifier: Programming Language :: Python :: 3
Classifier: License :: OSI Approved :: MIT License
Classifier: Operating System :: OS Independent
Requires-Python: >=3.6
License-File: LICENSE
